{
  "$schema": "https://raw.githubusercontent.com/electron-userland/electron-builder/master/packages/app-builder-lib/scheme.json",
  "appId": "io.tuist.Plasma",
  "productName": "Plasma",
  "directories": {
    "output": "release",
    "buildResources": "build"
  },
  "files": [
    "dist/**/*",
    "frontend/dist/**/*"
  ],
  "extraResources": [
    {
      "from": "bin",
      "to": "bin",
      "filter": ["**/*"]
    },
    {
      "from": "binaries",
      "to": "binaries",
      "filter": ["**/*"]
    }
  ],
  "mac": {
    "category": "public.app-category.developer-tools",
    "target": [
      {
        "target": "dmg",
        "arch": ["universal"]
      },
      {
        "target": "zip",
        "arch": ["universal"]
      }
    ],
    "icon": "build/icon.icns",
    "hardenedRuntime": true,
    "gatekeeperAssess": false,
    "entitlements": "build/entitlements.mac.plist",
    "entitlementsInherit": "build/entitlements.mac.plist"
  },
  "dmg": {
    "sign": false,
    "contents": [
      {
        "x": 130,
        "y": 220
      },
      {
        "x": 410,
        "y": 220,
        "type": "link",
        "path": "/Applications"
      }
    ]
  },
  "publish": {
    "provider": "github",
    "owner": "pepicrft",
    "repo": "Plasma"
  }
}
